CHANGES.rst
CONTRIBUTORS.rst
LICENSE
MANIFEST.in
README.rst
pytest.ini
requirements.txt
setup.cfg
setup.py
docs/source/conf.py
docs/source/index.rst
docs/source/install.rst
docs/source/modules.rst
docs/source/overview.rst
docs/source/sporco_cuda.cbpdn.rst
docs/source/sporco_cuda.util.rst
docs/source/_static/sporco.css
examples/big_cbpdn.py
examples/big_cbpdngrd.py
examples/cmp_cbpdn.py
examples/cmp_cbpdngrd.py
examples/cmp_cbpdngrdmsk.py
examples/cmp_cbpdnmsk.py
examples/cuda_util.py
examples/index.rst
examples/time_cbpdn.py
sporco_cuda/__init__.py
sporco_cuda/cbpdn.c
sporco_cuda/cbpdn.pyx
sporco_cuda/util.c
sporco_cuda/util.pyx
sporco_cuda.egg-info/PKG-INFO
sporco_cuda.egg-info/SOURCES.txt
sporco_cuda.egg-info/dependency_links.txt
sporco_cuda.egg-info/not-zip-safe
sporco_cuda.egg-info/requires.txt
sporco_cuda.egg-info/top_level.txt
sporco_cuda/src/algopt.h
sporco_cuda/src/cbpdn.cu
sporco_cuda/src/cbpdn.h
sporco_cuda/src/cbpdn_grd.cu
sporco_cuda/src/cbpdn_grd.h
sporco_cuda/src/cbpdn_kernels.cu
sporco_cuda/src/cbpdn_kernels.h
sporco_cuda/src/common.h
sporco_cuda/src/error_check.cuh
sporco_cuda/src/utils.cu
sporco_cuda/src/utils.h
sporco_cuda/tests/test_cbpdn.py
sporco_cuda/tests/test_util.py