Metadata-Version: 1.1
Name: sporco-cuda
Version: 0.0.5
Summary: SPORCO-CUDA: A CUDA extension package for SPORCO
Home-page: https://github.com/bwohlberg/sporco-cuda
Author: Gustavo Silva, Brendt Wohlberg
Author-email: gustavo.silva@pucp.edu.pe, brendt@ieee.org
License: BSD
Keywords: Convolutional Sparse Representations,Convolutional Sparse Coding,CUDA
Platform: Linux
Classifier: License :: OSI Approved :: BSD License
Classifier: Development Status :: 4 - Beta
Classifier: Intended Audience :: Education
Classifier: Intended Audience :: Science/Research
Classifier: License :: OSI Approved :: BSD License
Classifier: Operating System :: POSIX :: Linux
Classifier: Programming Language :: Python :: 2.7
Classifier: Programming Language :: Python :: 3
Classifier: Topic :: Scientific/Engineering :: Information Analysis
Classifier: Topic :: Scientific/Engineering :: Mathematics
Classifier: Topic :: Software Development :: Libraries :: Python Modules
